{
  "schema_version": 1,
  "app": "gitnexus",
  "source_version": "v1.6.1",
  "build_version": "1.6.1",
  "head_sha": "aabec0805797",
  "build_recipe_hash": "ce7622dc707bd008c2962da125759e0143216e92b0cd0716956cc55491e73737",
  "updated_at": "2026-04-14T01:09:52.983749+00:00",
  "images": {
    "gitnexus": "registry.lazycat.cloud/invokerlaw/codeeagle/lazycatimages:ca03def2f81296f8"
  },
  "source_images": {
    "gitnexus": "ghcr.io/codeeagle/lazycatimages:gitnexus_aabec0805797"
  },
  "source_digests": {
    "_primary": "sha256:afae7c7ec9eef74b439c26f0f5f1da09fae183f74b9bc3ec7ce1b2b9f5889abb"
  },
  "copy_image_events": [
    {
      "source_image": "ghcr.io/codeeagle/lazycatimages:gitnexus_aabec0805797",
      "target_image": "registry.lazycat.cloud/invokerlaw/codeeagle/lazycatimages:ca03def2f81296f8",
      "elapsed_seconds": 272.134,
      "saw_waiting": false,
      "saw_upload_started": false,
      "reused_existing": false,
      "kind": "primary"
    }
  ]
}
